{
  "run_id": "20260511_005205_sess-f39",
  "session_id": "sess-f39cc730",
  "started_at": "2026-05-10T16:52:05.300956+00:00",
  "ended_at": "2026-05-10T17:05:15.453138+00:00",
  "total_steps": 10,
  "sl_events": [
    {
      "type": "phase_return",
      "interrupted_phase": "combat",
      "old_state_version": 15,
      "new_state_version": 16,
      "session_id": "sess-f39cc730",
      "reason": "Returned to 'combat' phase after menu interruption, likely Save & Load",
      "step_index": 3,
      "timestamp": "2026-05-10T16:52:13.002348+00:00"
    },
    {
      "type": "phase_return",
      "interrupted_phase": "combat",
      "old_state_version": 19,
      "new_state_version": 20,
      "session_id": "sess-f39cc730",
      "reason": "Returned to 'combat' phase after menu interruption, likely Save & Load",
      "step_index": 7,
      "timestamp": "2026-05-10T16:52:23.982448+00:00"
    }
  ],
  "phases_visited": [
    "combat",
    "event",
    "menu"
  ]
}